Metadata-Version: 2.1
Name: boimmg
Version: 0.1.1
Summary: Find and tag Git commits based on version numbers in commit messages.
Home-page: https://initialcommit.com/projects/git-tagup
Author: João Capela
Author-email: jcapels96@gmail.com
License: UNKNOWN
Project-URL: Homepage, https://github.com/jcapels/boimmg
Keywords: git tag boimmg tagup tag-up version autotag auto-tag commit message
Platform: UNKNOWN
Classifier: Programming Language :: Python :: 3
Classifier: License :: OSI Approved :: MIT License
Classifier: Operating System :: OS Independent
Requires-Python: >=3.6
Requires-Dist: gitpython
Requires-Dist: pandas
Requires-Dist: cobra
Requires-Dist: cobrababel
Requires-Dist: neo4j
Requires-Dist: sympy
Requires-Dist: biocyc
Requires-Dist: biopython
Requires-Dist: requests
Requires-Dist: numpy
Requires-Dist: python-libsbml
